explain_errors/__init__.py
explain_errors/middleware.py
tests/__init__.py
tests/test_middleware.py
django_explain_errors-0.1.dist-info/LICENSE
django_explain_errors-0.1.dist-info/METADATA
django_explain_errors-0.1.dist-info/WHEEL
django_explain_errors-0.1.dist-info/top_level.txt
django_explain_errors-0.1.dist-info/RECORD
